[
  {
    "bootcampName": "Osona",
    "category": "Full Stack",
    "duration": "850",
    "characteristics": "From Osona",
    "former": "Sergi Virgili",
    "coformer": "Alexandra Galarza",
    "initialDate": "",
    "finalDate": ""
  },
  {
    "bootcampName": "FemTech",
    "category": "Back End",
    "duration": "850",
    "characteristics": "Women camp",
    "former": "Pedro Pedrito",
    "coformer": "Rocío",
    "initialDate": "",
    "finalDate": ""
  },
  {
    "bootcampName": "LaCiba",
    "category": "Front End",
    "duration": "300",
    "characteristics": "Women camp",
    "former": "Carlos Pinilla",
    "coformer": "Javier",
    "initialDate": "",
    "finalDate": ""
  }
]